Metadata-Version: 2.1
Name: odoo14-addon-pos_supplierinfo_barcode
Version: 14.0.1.0.1.dev8
Summary: Search products by supplier barcode
Home-page: https://github.com/OCA/pos
Author: TAKOBI, Odoo Community Association (OCA)
Author-email: support@odoo-community.org
License: LGPL-3
Classifier: Programming Language :: Python
Classifier: Framework :: Odoo
Classifier: Framework :: Odoo :: 14.0
Classifier: License :: OSI Approved :: GNU Lesser General Public License v3 (LGPLv3)
Classifier: Development Status :: 4 - Beta
Requires-Python: >=3.6
Requires-Dist: odoo14-addon-product-supplierinfo-barcode
Requires-Dist: odoo<14.1dev,>=14.0a
